slopify/__init__.py
slopify/applier.py
slopify/cli.py
slopify/dumper.py
slopify-0.2.2.dist-info/LICENSE
slopify-0.2.2.dist-info/METADATA
slopify-0.2.2.dist-info/WHEEL
slopify-0.2.2.dist-info/entry_points.txt
slopify-0.2.2.dist-info/RECORD
