Metadata-Version: 2.1
Name: slopify
Version: 0.2.2
Summary: 
Author: Mawhrin-Skel
Author-email: slapdrone@proton.me
Requires-Python: >=3.10,<4.0
Classifier: Programming Language :: Python :: 3
Classifier: Programming Language :: Python :: 3.10
Classifier: Programming Language :: Python :: 3.11
Classifier: Programming Language :: Python :: 3.12
Requires-Dist: black (>=23.11.0,<24.0.0)
Requires-Dist: jupyter (>=1.0.0,<2.0.0)
Requires-Dist: markdown-it-py (>=3.0.0,<4.0.0)
Requires-Dist: mypy (>=1.7.0,<2.0.0)
Requires-Dist: pathspec (>=0.11.2,<0.12.0)
Requires-Dist: pydantic (>=2.5.1,<3.0.0)
Requires-Dist: pyperclip (>=1.8.2,<2.0.0)
Requires-Dist: ruff (>=0.1.5,<0.2.0)
Requires-Dist: typer (>=0.9.0,<0.10.0)
